kontext_mcp/__init__.py
kontext_mcp/__main__.py
kontext_mcp/config.py
kontext_mcp/kontext.py
kontext_mcp/logging_util.py
kontext_mcp/register.py
kontext_mcp/server.py
kontext_mcp/tools.py
kontext_mcp-0.1.0.dist-info/METADATA
kontext_mcp-0.1.0.dist-info/WHEEL
kontext_mcp-0.1.0.dist-info/entry_points.txt
kontext_mcp-0.1.0.dist-info/licenses/LICENSE
kontext_mcp-0.1.0.dist-info/RECORD
