Metadata-Version: 2.4
Name: kontext-mcp
Version: 0.1.0
Summary: Portable, provider-agnostic memory on top of Azure Data Explorer (Kusto)
Project-URL: Homepage, https://github.com/danield137/kontext-mcp
Project-URL: Repository, https://github.com/danield137/kontext-mcp
Project-URL: Issues, https://github.com/danield137/kontext-mcp/issues
Project-URL: Documentation, https://github.com/danield137/kontext-mcp#readme
Author: Kontext Team
License: MIT
License-File: LICENSE
Keywords: agents,ai,azure,embeddings,kusto,mcp,memory
Classifier: Development Status :: 3 - Alpha
Classifier: Intended Audience :: Developers
Classifier: License :: OSI Approved :: MIT License
Classifier: Operating System :: OS Independent
Classifier: Programming Language :: Python :: 3
Classifier: Programming Language :: Python :: 3.10
Classifier: Programming Language :: Python :: 3.11
Classifier: Programming Language :: Python :: 3.12
Classifier: Topic :: Scientific/Engineering :: Artificial Intelligence
Classifier: Topic :: Software Development :: Libraries :: Python Modules
Requires-Python: >=3.10
Requires-Dist: azure-kusto-data>=4.0.0
Requires-Dist: azure-kusto-ingest>=4.0.0
Requires-Dist: mcp>=1.0.0
Requires-Dist: python-dotenv>=1.0.0
Provides-Extra: dev
Requires-Dist: black>=23.0.0; extra == 'dev'
Requires-Dist: flake8>=6.0.0; extra == 'dev'
Requires-Dist: isort>=5.12.0; extra == 'dev'
Requires-Dist: mypy>=1.0.0; extra == 'dev'
Requires-Dist: pytest-cov>=4.0.0; extra == 'dev'
Requires-Dist: pytest-mock>=3.10.0; extra == 'dev'
Requires-Dist: pytest>=7.0.0; extra == 'dev'
